LICENSE
README.md
pyproject.toml
setup.py
src/allure_pytest_yaml.egg-info/PKG-INFO
src/allure_pytest_yaml.egg-info/SOURCES.txt
src/allure_pytest_yaml.egg-info/dependency_links.txt
src/allure_pytest_yaml.egg-info/requires.txt
src/allure_pytest_yaml.egg-info/top_level.txt
src/pytest_yaml_fei/__init__.py
src/pytest_yaml_fei/create_funtion.py
src/pytest_yaml_fei/db.py
src/pytest_yaml_fei/exceptions.py
src/pytest_yaml_fei/extract.py
src/pytest_yaml_fei/http_session.py
src/pytest_yaml_fei/log.py
src/pytest_yaml_fei/my_builtins.py
src/pytest_yaml_fei/parser.py
src/pytest_yaml_fei/plugin.py
src/pytest_yaml_fei/render_template_obj.py
src/pytest_yaml_fei/report_notify.py
src/pytest_yaml_fei/request_session.py
src/pytest_yaml_fei/runner.py
src/pytest_yaml_fei/start_project.py
src/pytest_yaml_fei/swagger_parser.py
src/pytest_yaml_fei/validate.py